jupyter_kernel_singular/__init__.py
jupyter_kernel_singular/__main__.py
jupyter_kernel_singular/kernel.py
passagemath_singular_jupyterkernel-0.9.9.1.data/data/etc/jupyter/nbconfig/notebook.d/singular-mode.json
passagemath_singular_jupyterkernel-0.9.9.1.data/data/share/jupyter/kernels/singular/kernel.json
passagemath_singular_jupyterkernel-0.9.9.1.data/data/share/jupyter/kernels/singular/logo-32x32.png
passagemath_singular_jupyterkernel-0.9.9.1.data/data/share/jupyter/kernels/singular/logo-64x64.png
passagemath_singular_jupyterkernel-0.9.9.1.data/data/share/jupyter/nbextensions/singular-mode/main.js
passagemath_singular_jupyterkernel-0.9.9.1.data/data/share/jupyter/nbextensions/singular-mode/singular.js
passagemath_singular_jupyterkernel-0.9.9.1.dist-info/licenses/COPYING
passagemath_singular_jupyterkernel-0.9.9.1.dist-info/licenses/LICENSE
passagemath_singular_jupyterkernel-0.9.9.1.dist-info/METADATA
passagemath_singular_jupyterkernel-0.9.9.1.dist-info/WHEEL
passagemath_singular_jupyterkernel-0.9.9.1.dist-info/top_level.txt
passagemath_singular_jupyterkernel-0.9.9.1.dist-info/RECORD
