Metadata-Version: 2.4
Name: passagemath-singular-jupyterkernel
Version: 0.9.9.1
Summary: A Jupyter kernel for Singular (passagemath fork of jupyter_kernel_singular)
Home-page: https://github.com/passagemath/passagemath-singular-jupyterkernel
Author: Sebastian Gutsche
Author-email: sebastian.gutsche@gmail.com
Maintainer: Matthias Koeppe and passagemath contributors
License-File: LICENSE
License-File: COPYING
Dynamic: author
Dynamic: author-email
Dynamic: home-page
Dynamic: license-file
Dynamic: maintainer
Dynamic: summary
